{
    "data": {
        "host_id": "3b26908e-ab39-11f0-bce4-22a1b8d92490",
        "host_nm": "test_tenant-compute-01",
        "pfrm_host_id": "142afe84-ca5f-46ed-a5b4-96f3056fe782",
        "host_ip": "192.168.132.44",
        "hyper_typ": "QEMU",
        "host_descp": null,
        "host_sts_cd": "P003NOR",
        "host_sts_cd_nm": "정상",
        "vcpu_tot_cnt": "96",
        "vcpu_usg_cnt": "25",
        "mem_tot_capa": "125",
        "mem_usg_capa": "49",
        "str_tot_capa": "1536",
        "str_usg_capa": "0",
        "vm_tot_cnt": "5",
        "vm_usg_cnt": "4",
        "zone_assgn_yn": "Y",
        "reg_id": "bf8eb4fd-ab36-11f0-8557-3a7bf606d4cf",
        "reg_nm": "***",
        "reg_conn_id": "***",
        "reg_ts": "2025-10-17 18:11:14",
        "mod_id": "platform.scheduler",
        "mod_nm": null,
        "mod_conn_id": null,
        "mod_ts": "2026-03-31 11:11:00",
        "tnt_id": "02157c4b5e534cb492ed5c886d3b44d7",
        "tnt_assgn_yn": "Y",
        "zone_nm": "Default Zone",
        "host_grp_nm": "Default Zone",
        "ha_auto_mng_yn": null
    }
}
